CHANGELOG.rst
MANIFEST.in
README.rst
setup.py
src/sact/__init__.py
src/sact.recipe.gitrepository.egg-info/PKG-INFO
src/sact.recipe.gitrepository.egg-info/SOURCES.txt
src/sact.recipe.gitrepository.egg-info/dependency_links.txt
src/sact.recipe.gitrepository.egg-info/entry_points.txt
src/sact.recipe.gitrepository.egg-info/namespace_packages.txt
src/sact.recipe.gitrepository.egg-info/not-zip-safe
src/sact.recipe.gitrepository.egg-info/requires.txt
src/sact.recipe.gitrepository.egg-info/top_level.txt
src/sact/recipe/__init__.py
src/sact/recipe/gitrepository/__init__.py
src/sact/recipe/gitrepository/tests.py