Metadata-Version: 1.1
Name: sact.recipe.gitrepository
Version: 1.0
Summary: Buildout recipe for fetching sources in a git repository
Home-page: http://github.com/securactive/sact.recipe.gitrepository
Author: Sebastien Douche
Author-email: sdouche@gmail.com
License: BSD
Keywords: zc.buildout recipe git
Platform: UNKNOWN
Classifier: Framework :: Buildout
Classifier: Intended Audience :: Developers
Classifier: License :: OSI Approved :: BSD License
Classifier: Programming Language :: Python
Classifier: Programming Language :: Python :: 2
Classifier: Programming Language :: Python :: 3
Classifier: Topic :: Software Development
Classifier: Topic :: Software Development :: Pre-processors
